.gitignore
.travis.yml
CONTRIBUTORS.md
LICENSE.md
README-vi.md
README.md
README.rst
codecov.yml
requirements.txt
setup.py
tox.ini
.eggs/README.txt
.eggs/pytest_runner-4.2-py2.7.egg/ptr.py
.eggs/pytest_runner-4.2-py2.7.egg/EGG-INFO/DESCRIPTION.rst
.eggs/pytest_runner-4.2-py2.7.egg/EGG-INFO/LICENSE.txt
.eggs/pytest_runner-4.2-py2.7.egg/EGG-INFO/PKG-INFO
.eggs/pytest_runner-4.2-py2.7.egg/EGG-INFO/RECORD
.eggs/pytest_runner-4.2-py2.7.egg/EGG-INFO/WHEEL
.eggs/pytest_runner-4.2-py2.7.egg/EGG-INFO/entry_points.txt
.eggs/pytest_runner-4.2-py2.7.egg/EGG-INFO/metadata.json
.eggs/pytest_runner-4.2-py2.7.egg/EGG-INFO/namespace_packages.txt
.eggs/pytest_runner-4.2-py2.7.egg/EGG-INFO/requires.txt
.eggs/pytest_runner-4.2-py2.7.egg/EGG-INFO/top_level.txt
.eggs/setuptools_scm-2.0.0-py2.7.egg/EGG-INFO/LICENSE.txt
.eggs/setuptools_scm-2.0.0-py2.7.egg/EGG-INFO/PKG-INFO
.eggs/setuptools_scm-2.0.0-py2.7.egg/EGG-INFO/RECORD
.eggs/setuptools_scm-2.0.0-py2.7.egg/EGG-INFO/WHEEL
.eggs/setuptools_scm-2.0.0-py2.7.egg/EGG-INFO/entry_points.txt
.eggs/setuptools_scm-2.0.0-py2.7.egg/EGG-INFO/top_level.txt
.eggs/setuptools_scm-2.0.0-py2.7.egg/EGG-INFO/zip-safe
.eggs/setuptools_scm-2.0.0-py2.7.egg/setuptools_scm/__init__.py
.eggs/setuptools_scm-2.0.0-py2.7.egg/setuptools_scm/__main__.py
.eggs/setuptools_scm-2.0.0-py2.7.egg/setuptools_scm/discover.py
.eggs/setuptools_scm-2.0.0-py2.7.egg/setuptools_scm/git.py
.eggs/setuptools_scm-2.0.0-py2.7.egg/setuptools_scm/hacks.py
.eggs/setuptools_scm-2.0.0-py2.7.egg/setuptools_scm/hg.py
.eggs/setuptools_scm-2.0.0-py2.7.egg/setuptools_scm/integration.py
.eggs/setuptools_scm-2.0.0-py2.7.egg/setuptools_scm/utils.py
.eggs/setuptools_scm-2.0.0-py2.7.egg/setuptools_scm/version.py
.eggs/setuptools_scm-2.0.0-py2.7.egg/setuptools_scm/win_py31_compat.py
dist/muted_http_request_randomizer-0.0.4.tar.gz
dist/muted_http_request_randomizer-0.0.5.tar.gz
dist/muted_http_request_randomizer-0.0.6.tar.gz
muted_http_request_randomizer/__init__.py
muted_http_request_randomizer.egg-info/PKG-INFO
muted_http_request_randomizer.egg-info/SOURCES.txt
muted_http_request_randomizer.egg-info/dependency_links.txt
muted_http_request_randomizer.egg-info/entry_points.txt
muted_http_request_randomizer.egg-info/not-zip-safe
muted_http_request_randomizer.egg-info/requires.txt
muted_http_request_randomizer.egg-info/top_level.txt
muted_http_request_randomizer/requests/__init__.py
muted_http_request_randomizer/requests/data/user_agents.txt
muted_http_request_randomizer/requests/errors/ParserExceptions.py
muted_http_request_randomizer/requests/errors/ProxyListException.py
muted_http_request_randomizer/requests/errors/__init__.py
muted_http_request_randomizer/requests/parsers/FreeProxyParser.py
muted_http_request_randomizer/requests/parsers/ProxyForEuParser.py
muted_http_request_randomizer/requests/parsers/RebroWeeblyParser.py
muted_http_request_randomizer/requests/parsers/SamairProxyParser.py
muted_http_request_randomizer/requests/parsers/UrlParser.py
muted_http_request_randomizer/requests/parsers/__init__.py
muted_http_request_randomizer/requests/proxy/ProxyObject.py
muted_http_request_randomizer/requests/proxy/__init__.py
muted_http_request_randomizer/requests/proxy/requestProxy.py
muted_http_request_randomizer/requests/runners/__init__.py
muted_http_request_randomizer/requests/runners/proxyList.py
