Metadata-Version: 1.1
Name: muted-http-request-randomizer
Version: 0.0.7
Summary: muted HRR
Home-page: http://pgaref.com/blog/python-proxy
Author: Panagiotis Garefalakis, Wentao Lu
Author-email: pangaref@gmail.com, wentao@wentaolu.com
License: MIT
Platform: any
Classifier: Programming Language :: Python
Classifier: Programming Language :: Python :: 2
Classifier: Programming Language :: Python :: 3
Classifier: Operating System :: OS Independent
Classifier: Development Status :: 4 - Beta
Classifier: Natural Language :: English
Classifier: Environment :: Web Environment
Classifier: Intended Audience :: Developers
Classifier: Topic :: Internet :: WWW/HTTP
Classifier: License :: OSI Approved :: MIT License
Classifier: Topic :: Software Development :: Libraries :: Python Modules
